CanvasGroupy/__init__.py
CanvasGroupy/_modidx.py
CanvasGroupy/assign.py
CanvasGroupy/canvas.py
CanvasGroupy/github.py
CanvasGroupy/grading.py
CanvasGroupy-0.0.3.dist-info/LICENSE
CanvasGroupy-0.0.3.dist-info/METADATA
CanvasGroupy-0.0.3.dist-info/WHEEL
CanvasGroupy-0.0.3.dist-info/entry_points.txt
CanvasGroupy-0.0.3.dist-info/top_level.txt
CanvasGroupy-0.0.3.dist-info/RECORD
