Metadata-Version: 2.1
Name: CanvasGroupy
Version: 0.0.3
Summary: Canvas Grouping Python Script
Home-page: https://github.com/FleischerResearchLab/CanvasGroupy
Author: scottyang
Author-email: yuy004@ucsd.edu
License: Apache Software License 2.0
Keywords: nbdev jupyter notebook python
Platform: UNKNOWN
Classifier: Development Status :: 4 - Beta
Classifier: Intended Audience :: Developers
Classifier: Natural Language :: English
Classifier: Programming Language :: Python :: 3.7
Classifier: Programming Language :: Python :: 3.8
Classifier: Programming Language :: Python :: 3.9
Classifier: Programming Language :: Python :: 3.10
Classifier: License :: OSI Approved :: Apache Software License
Requires-Python: >=3.7
License-File: LICENSE
Requires-Dist: fastcore
Requires-Dist: pandas
Requires-Dist: numpy
Requires-Dist: PyGithub
Requires-Dist: canvasapi
Provides-Extra: dev
